{"version":1,"resource":"file:///home/srj/repos/srj-17/library/script.js","entries":[{"id":"JfRE.js","timestamp":1722567046499},{"id":"65Zm.js","timestamp":1722567065183},{"id":"My33.js","timestamp":1722567084812},{"id":"SSl2.js","timestamp":1722567113304},{"id":"bxxI.js","timestamp":1722567128569},{"id":"wbO0.js","timestamp":1722567146721},{"id":"K44L.js","timestamp":1722567177298},{"id":"sr6S.js","timestamp":1722567206254},{"id":"aJS9.js","timestamp":1722567358310},{"id":"ZQkU.js","timestamp":1722567374259},{"id":"BPSz.js","source":"undoRedo.source","timestamp":1722567376823},{"id":"CSrt.js","timestamp":1722567410708},{"id":"7TBy.js","timestamp":1722567477545},{"id":"yH1x.js","timestamp":1722567520579},{"id":"G2sy.js","timestamp":1722567544927},{"id":"YJnX.js","timestamp":1722567619066},{"id":"0Ctf.js","timestamp":1722567630914},{"id":"uSwA.js","timestamp":1722567660431},{"id":"om38.js","timestamp":1722584466137},{"id":"S0sL.js","timestamp":1722584569279},{"id":"tTte.js","timestamp":1722584622096},{"id":"0voQ.js","timestamp":1722584667112},{"id":"vcVq.js","timestamp":1722584718257},{"id":"4MF8.js","timestamp":1722584732889},{"id":"enBw.js","timestamp":1722584754757},{"id":"hn8o.js","timestamp":1722584815317},{"id":"mujE.js","timestamp":1722584826141},{"id":"wNM3.js","timestamp":1722584864625},{"id":"CVLf.js","timestamp":1722584918945},{"id":"GMnO.js","timestamp":1722585068324},{"id":"PrZu.js","timestamp":1722585605293},{"id":"HVTM.js","timestamp":1722585615342},{"id":"SJPE.js","timestamp":1722585852087},{"id":"dit3.js","timestamp":1722585932046},{"id":"jOMI.js","timestamp":1722585973056},{"id":"22kg.js","timestamp":1722586141207},{"id":"Vsdv.js","timestamp":1722587156556},{"id":"ZPup.js","timestamp":1722589575190},{"id":"cqfg.js","timestamp":1722589588158},{"id":"Nh0M.js","timestamp":1722590030482},{"id":"rC0f.js","timestamp":1722590073236},{"id":"ofXs.js","timestamp":1722590193537},{"id":"fXgg.js","timestamp":1722590234576},{"id":"S5oz.js","timestamp":1722590323787},{"id":"pYQD.js","timestamp":1722590347766},{"id":"KzEz.js","timestamp":1722590402644},{"id":"Z6sf.js","timestamp":1722590418942},{"id":"ttHy.js","timestamp":1722590468363},{"id":"gy0J.js","timestamp":1722590505586},{"id":"PgM3.js","timestamp":1722590582168}]}