{"version":1,"resource":"file:///home/srj/repos/js/mdn_intro_js/index.html","entries":[{"id":"wNFr.html","timestamp":1718203219715},{"id":"ZZox.html","timestamp":1718203242299},{"id":"cqRq.html","timestamp":1718203299135},{"id":"Oytt.html","timestamp":1718203340076},{"id":"Hd5U.html","timestamp":1718203392896},{"id":"GtwR.html","timestamp":1718203430456},{"id":"4CE0.html","timestamp":1718204966169},{"id":"s6Bs.html","timestamp":1718205162339},{"id":"ETad.html","timestamp":1718205178200},{"id":"bH97.html","timestamp":1718205284925},{"id":"Kwuz.html","timestamp":1718205299577},{"id":"20aO.html","timestamp":1718205328143},{"id":"1byY.html","timestamp":1718205350425},{"id":"rSSM.html","timestamp":1718205410848},{"id":"sJNT.html","timestamp":1718205426153},{"id":"Lo7R.html","timestamp":1718205514013}]}