{"version":1,"resource":"file:///home/srj/repos/ranhoodlum/html-and-css/grid/positioning-grid-items/style.css","entries":[{"id":"9w49.css","timestamp":1721807700146},{"id":"kJih.css","timestamp":1721807753595},{"id":"QwLt.css","timestamp":1721807764952},{"id":"MmCG.css","timestamp":1721807802146},{"id":"klEI.css","timestamp":1721807855790},{"id":"6LEb.css","timestamp":1721808217481},{"id":"7pip.css","timestamp":1721808229021},{"id":"yxkl.css","timestamp":1721808298628},{"id":"6U0M.css","timestamp":1721808351106},{"id":"K1Z6.css","timestamp":1721808592505},{"id":"nyt8.css","timestamp":1721808618885},{"id":"65MQ.css","timestamp":1721808685667},{"id":"DZXY.css","timestamp":1721808712768},{"id":"PdQf.css","timestamp":1721808727280},{"id":"wyGT.css","timestamp":1721808745440},{"id":"NmGO.css","timestamp":1721808767185},{"id":"QkC6.css","timestamp":1721808855191},{"id":"8HmV.css","timestamp":1721808893444},{"id":"wLJY.css","timestamp":1721808944261},{"id":"CxCN.css","timestamp":1721808976593}]}